anipy_api/__init__.py
anipy_api/anilist.py
anipy_api/anime.py
anipy_api/download.py
anipy_api/error.py
anipy_api/locallist.py
anipy_api/mal.py
anipy_api/player/__init__.py
anipy_api/player/base.py
anipy_api/player/player.py
anipy_api/player/players/__init__.py
anipy_api/player/players/iina.py
anipy_api/player/players/mpv.py
anipy_api/player/players/mpv_control.py
anipy_api/player/players/syncplay.py
anipy_api/player/players/vlc.py
anipy_api/provider/__init__.py
anipy_api/provider/base.py
anipy_api/provider/filter.py
anipy_api/provider/provider.py
anipy_api/provider/providers/__init__.py
anipy_api/provider/providers/allanime_provider.py
anipy_api/provider/providers/animekai_provider.py
anipy_api/provider/providers/native_provider.py
anipy_api/provider/utils.py
anipy_api-3.8.3.dist-info/METADATA
anipy_api-3.8.3.dist-info/WHEEL
anipy_api-3.8.3.dist-info/RECORD
