Metadata-Version: 2.4
Name: anipy-api
Version: 3.8.3
Summary: api for anipy-cli
License: GPL-3.0
Keywords: anime,api
Author: sdaqo
Author-email: sdaqo.dev@protonmail.com
Requires-Python: >=3.10,<4.0
Classifier: License :: OSI Approved :: GNU General Public License v3 (GPLv3)
Classifier: Programming Language :: Python :: 3
Classifier: Programming Language :: Python :: 3.10
Classifier: Programming Language :: Python :: 3.11
Classifier: Programming Language :: Python :: 3.12
Classifier: Programming Language :: Python :: 3.13
Classifier: Programming Language :: Python :: 3.14
Requires-Dist: beautifulsoup4 (>=4.12.3,<5.0.0)
Requires-Dist: dataclasses-json (>=0.6.4,<0.7.0)
Requires-Dist: levenshtein (>=0.27.3,<0.28.0)
Requires-Dist: m3u8 (>=4.1.0,<5.0.0)
Requires-Dist: pycountry (>=24.6.1,<25.0.0)
Requires-Dist: pycryptodomex (>=3.20.0,<4.0.0)
Requires-Dist: python-ffmpeg (>=2.0.11,<3.0.0)
Requires-Dist: python-mpv (>=1.0.6,<2.0.0)
Requires-Dist: rapidfuzz (>=3.14.0,<4.0.0)
Requires-Dist: requests (>=2.32.0,<3.0.0)
Requires-Dist: simpleeval (>=1.0.3,<2.0.0)
Project-URL: Bug Tracker, https://github.com/sdaqo/anipy-cli/issues
Project-URL: Documentation, https://sdaqo.github.io/anipy-cli/getting-started-api
Project-URL: Homepage, https://sdaqo.github.io/anipy-cli
Project-URL: Repository, https://github.com/sdaqo/anipy-cli
